MANIFEST.in
README.txt
setup.cfg
setup.py
docs/HISTORY.txt
horae/__init__.py
horae.usersandgroups.egg-info/PKG-INFO
horae.usersandgroups.egg-info/SOURCES.txt
horae.usersandgroups.egg-info/dependency_links.txt
horae.usersandgroups.egg-info/entry_points.txt
horae.usersandgroups.egg-info/namespace_packages.txt
horae.usersandgroups.egg-info/not-zip-safe
horae.usersandgroups.egg-info/requires.txt
horae.usersandgroups.egg-info/top_level.txt
horae/usersandgroups/__init__.py
horae/usersandgroups/configure.zcml
horae/usersandgroups/group.py
horae/usersandgroups/interfaces.py
horae/usersandgroups/providers.py
horae/usersandgroups/user.py
horae/usersandgroups/views.py
horae/usersandgroups/locales/horae.usersandgroups.pot
horae/usersandgroups/locales/de/LC_MESSAGES/horae.usersandgroups.mo
horae/usersandgroups/locales/de/LC_MESSAGES/horae.usersandgroups.po