Metadata-Version: 1.0
Name: horae.usersandgroups
Version: 1.0a1
Summary: Provides a persistent implementation of users and groups for the Horae resource planning system
Home-page: UNKNOWN
Author: Simon Kaeser
Author-email: skaeser@gmail.com
License: GPL
Platform: UNKNOWN
Classifier: Programming Language :: Python
Classifier: Topic :: Software Development :: Libraries :: Python Modules
